markdown2textile/__about__.py
markdown2textile/__init__.py
markdown2textile/__main__.py
markdown2textile/m2t_pandoc_filter.py
markdown2textile/t2m_pandoc_filter.py
markdown2textile/cli/__init__.py
markdown2textile-0.2.2.dist-info/METADATA
markdown2textile-0.2.2.dist-info/WHEEL
markdown2textile-0.2.2.dist-info/entry_points.txt
markdown2textile-0.2.2.dist-info/licenses/LICENSE.txt
markdown2textile-0.2.2.dist-info/RECORD
