Metadata-Version: 2.3
Name: markdown2textile
Version: 0.2.2
Summary: This is a simple tool to convert markdown to textile. It's useful for handling redmine wiki.
Project-URL: Documentation, https://github.com/magicwenli/markdown2textile#readme
Project-URL: Issues, https://github.com/magicwenli/markdown2textile/issues
Project-URL: Source, https://github.com/magicwenli/markdown2textile
Author-email: irisTa56 <unknow@1.com>, magicwenli <yxnian@outlook.com>
License-Expression: MIT
License-File: LICENSE.txt
Classifier: Development Status :: 4 - Beta
Classifier: Programming Language :: Python
Classifier: Programming Language :: Python :: 3.8
Classifier: Programming Language :: Python :: 3.9
Classifier: Programming Language :: Python :: 3.10
Classifier: Programming Language :: Python :: 3.11
Classifier: Programming Language :: Python :: 3.12
Classifier: Programming Language :: Python :: Implementation :: CPython
Classifier: Programming Language :: Python :: Implementation :: PyPy
Requires-Python: >=3.8
Requires-Dist: click
Requires-Dist: panflute
Requires-Dist: pypandoc
